nornir_http/__init__.py
nornir_http/result.py
nornir_http/tasks.py
nornir_http-0.1.3.dist-info/METADATA
nornir_http-0.1.3.dist-info/WHEEL
nornir_http-0.1.3.dist-info/RECORD
